{".class":"MypyFile","_fullname":"pyadtpulse.util","future_import_flags":[],"is_partial_stub_package":false,"is_stub":false,"names":{".class":"SymbolTable","ALLOWABLE_CHARACTERS":{".class":"SymbolTableNode","kind":"Gdef","node":{".class":"Var","flags":["is_inferred","has_explicit_value"],"fullname":"pyadtpulse.util.ALLOWABLE_CHARACTERS","name":"ALLOWABLE_CHARACTERS","type":{".class":"Instance","args":["builtins.str"],"type_ref":"builtins.list"}}},"AuthenticationException":{".class":"SymbolTableNode","kind":"Gdef","node":{".class":"TypeInfo","_promote":[],"abstract_attributes":[],"alt_promote":null,"bases":["builtins.RuntimeError"],"dataclass_transform_spec":null,"declared_metaclass":null,"defn":{".class":"ClassDef","fullname":"pyadtpulse.util.AuthenticationException","name":"AuthenticationException","type_vars":[]},"deletable_attributes":[],"flags":[],"fullname":"pyadtpulse.util.AuthenticationException","has_param_spec_type":false,"metaclass_type":null,"metadata":{},"module_name":"pyadtpulse.util","mro":["pyadtpulse.util.AuthenticationException","builtins.RuntimeError","builtins.Exception","builtins.BaseException","builtins.object"],"names":{".class":"SymbolTable","__init":{".class":"SymbolTableNode","kind":"Mdef","node":{".class":"FuncDef","abstract_status":0,"arg_kinds":[0,0],"arg_names":["self","username"],"dataclass_transform_spec":null,"flags":[],"fullname":"pyadtpulse.util.AuthenticationException.__init","name":"__init","type":{".class":"CallableType","arg_kinds":[0,0],"arg_names":["self","username"],"arg_types":["pyadtpulse.util.AuthenticationException","builtins.str"],"bound_args":[],"def_extras":{"first_arg":"self"},"fallback":"builtins.function","from_concatenate":false,"implicit":false,"is_ellipsis_args":false,"name":"__init of AuthenticationException","ret_type":{".class":"AnyType","missing_import_name":null,"source_any":null,"type_of_any":1},"type_guard":null,"unpack_kwargs":false,"variables":[]}}}},"self_type":null,"slots":null,"tuple_type":null,"type_vars":[],"typeddict_type":null}},"BeautifulSoup":{".class":"SymbolTableNode","kind":"Gdef","node":{".class":"Var","flags":["is_suppressed_import","is_ready","is_inferred"],"fullname":"pyadtpulse.util.BeautifulSoup","name":"BeautifulSoup","type":{".class":"AnyType","missing_import_name":"pyadtpulse.util.BeautifulSoup","source_any":null,"type_of_any":3}}},"ClientResponse":{".class":"SymbolTableNode","cross_ref":"aiohttp.client_reqrep.ClientResponse","kind":"Gdef"},"DebugRLock":{".class":"SymbolTableNode","kind":"Gdef","node":{".class":"TypeInfo","_promote":[],"abstract_attributes":[],"alt_promote":null,"bases":["builtins.object"],"dataclass_transform_spec":null,"declared_metaclass":null,"defn":{".class":"ClassDef","fullname":"pyadtpulse.util.DebugRLock","name":"DebugRLock","type_vars":[]},"deletable_attributes":[],"flags":[],"fullname":"pyadtpulse.util.DebugRLock","has_param_spec_type":false,"metaclass_type":null,"metadata":{},"module_name":"pyadtpulse.util","mro":["pyadtpulse.util.DebugRLock","builtins.object"],"names":{".class":"SymbolTable","_Rlock":{".class":"SymbolTableNode","implicit":true,"kind":"Mdef","node":{".class":"Var","flags":["is_inferred"],"fullname":"pyadtpulse.util.DebugRLock._Rlock","name":"_Rlock","type":"threading._RLock"}},"__enter__":{".class":"SymbolTableNode","kind":"Mdef","node":{".class":"Var","flags":["is_initialized_in_class","is_inferred","has_explicit_value"],"fullname":"pyadtpulse.util.DebugRLock.__enter__","name":"__enter__","type":{".class":"CallableType","arg_kinds":[0,1,1],"arg_names":["self","blocking","timeout"],"arg_types":["pyadtpulse.util.DebugRLock","builtins.bool","builtins.float"],"bound_args":[],"def_extras":{"first_arg":"self"},"fallback":"builtins.function","from_concatenate":false,"implicit":false,"is_ellipsis_args":false,"name":null,"ret_type":"builtins.bool","type_guard":null,"unpack_kwargs":false,"variables":[]}}},"__exit__":{".class":"SymbolTableNode","kind":"Mdef","node":{".class":"FuncDef","abstract_status":0,"arg_kinds":[0,0,0,0],"arg_names":[null,null,null,null],"dataclass_transform_spec":null,"flags":[],"fullname":"pyadtpulse.util.DebugRLock.__exit__","name":"__exit__","type":null}},"__init__":{".class":"SymbolTableNode","kind":"Mdef","node":{".class":"FuncDef","abstract_status":0,"arg_kinds":[0,0],"arg_names":["self","name"],"dataclass_transform_spec":null,"flags":[],"fullname":"pyadtpulse.util.DebugRLock.__init__","name":"__init__","type":{".class":"CallableType","arg_kinds":[0,0],"arg_names":["self","name"],"arg_types":["pyadtpulse.util.DebugRLock","builtins.str"],"bound_args":[],"def_extras":{"first_arg":"self"},"fallback":"builtins.function","from_concatenate":false,"implicit":false,"is_ellipsis_args":false,"name":"__init__ of DebugRLock","ret_type":{".class":"NoneType"},"type_guard":null,"unpack_kwargs":false,"variables":[]}}},"_lock_name":{".class":"SymbolTableNode","implicit":true,"kind":"Mdef","node":{".class":"Var","flags":["is_inferred"],"fullname":"pyadtpulse.util.DebugRLock._lock_name","name":"_lock_name","type":"builtins.str"}},"acquire":{".class":"SymbolTableNode","kind":"Mdef","node":{".class":"FuncDef","abstract_status":0,"arg_kinds":[0,1,1],"arg_names":["self","blocking","timeout"],"dataclass_transform_spec":null,"flags":[],"fullname":"pyadtpulse.util.DebugRLock.acquire","name":"acquire","type":{".class":"CallableType","arg_kinds":[0,1,1],"arg_names":["self","blocking","timeout"],"arg_types":["pyadtpulse.util.DebugRLock","builtins.bool","builtins.float"],"bound_args":[],"def_extras":{"first_arg":"self"},"fallback":"builtins.function","from_concatenate":false,"implicit":false,"is_ellipsis_args":false,"name":"acquire of DebugRLock","ret_type":"builtins.bool","type_guard":null,"unpack_kwargs":false,"variables":[]}}},"release":{".class":"SymbolTableNode","kind":"Mdef","node":{".class":"FuncDef","abstract_status":0,"arg_kinds":[0],"arg_names":["self"],"dataclass_transform_spec":null,"flags":[],"fullname":"pyadtpulse.util.DebugRLock.release","name":"release","type":{".class":"CallableType","arg_kinds":[0],"arg_names":["self"],"arg_types":["pyadtpulse.util.DebugRLock"],"bound_args":[],"def_extras":{"first_arg":"self"},"fallback":"builtins.function","from_concatenate":false,"implicit":false,"is_ellipsis_args":false,"name":"release of DebugRLock","ret_type":{".class":"NoneType"},"type_guard":null,"unpack_kwargs":false,"variables":[]}}}},"self_type":null,"slots":null,"tuple_type":null,"type_vars":[],"typeddict_type":null}},"FINGERPRINT_LENGTH":{".class":"SymbolTableNode","kind":"Gdef","node":{".class":"Var","flags":["is_ready","is_inferred","has_explicit_value"],"fullname":"pyadtpulse.util.FINGERPRINT_LENGTH","name":"FINGERPRINT_LENGTH","type":"builtins.int"}},"FINGERPRINT_RANGE_LEN":{".class":"SymbolTableNode","kind":"Gdef","node":{".class":"Var","flags":["is_inferred","has_explicit_value"],"fullname":"pyadtpulse.util.FINGERPRINT_RANGE_LEN","name":"FINGERPRINT_RANGE_LEN","type":"builtins.int"}},"LOG":{".class":"SymbolTableNode","kind":"Gdef","node":{".class":"Var","flags":["is_inferred","has_explicit_value"],"fullname":"pyadtpulse.util.LOG","name":"LOG","type":"logging.Logger"}},"Optional":{".class":"SymbolTableNode","cross_ref":"typing.Optional","kind":"Gdef"},"Path":{".class":"SymbolTableNode","cross_ref":"pathlib.Path","kind":"Gdef"},"RLock":{".class":"SymbolTableNode","cross_ref":"threading.RLock","kind":"Gdef"},"__annotations__":{".class":"SymbolTableNode","kind":"Gdef","node":{".class":"Var","flags":["is_ready"],"fullname":"pyadtpulse.util.__annotations__","name":"__annotations__","type":{".class":"Instance","args":["builtins.str",{".class":"AnyType","missing_import_name":null,"source_any":null,"type_of_any":6}],"type_ref":"builtins.dict"}}},"__doc__":{".class":"SymbolTableNode","kind":"Gdef","node":{".class":"Var","flags":["is_ready"],"fullname":"pyadtpulse.util.__doc__","name":"__doc__","type":"builtins.str"}},"__file__":{".class":"SymbolTableNode","kind":"Gdef","node":{".class":"Var","flags":["is_ready"],"fullname":"pyadtpulse.util.__file__","name":"__file__","type":"builtins.str"}},"__name__":{".class":"SymbolTableNode","kind":"Gdef","node":{".class":"Var","flags":["is_ready"],"fullname":"pyadtpulse.util.__name__","name":"__name__","type":"builtins.str"}},"__package__":{".class":"SymbolTableNode","kind":"Gdef","node":{".class":"Var","flags":["is_ready"],"fullname":"pyadtpulse.util.__package__","name":"__package__","type":"builtins.str"}},"close_response":{".class":"SymbolTableNode","kind":"Gdef","node":{".class":"FuncDef","abstract_status":0,"arg_kinds":[0],"arg_names":["response"],"dataclass_transform_spec":null,"flags":[],"fullname":"pyadtpulse.util.close_response","name":"close_response","type":{".class":"CallableType","arg_kinds":[0],"arg_names":["response"],"arg_types":[{".class":"UnionType","items":["aiohttp.client_reqrep.ClientResponse",{".class":"NoneType"}]}],"bound_args":[],"def_extras":{"first_arg":null},"fallback":"builtins.function","from_concatenate":false,"implicit":false,"is_ellipsis_args":false,"name":"close_response","ret_type":{".class":"NoneType"},"type_guard":null,"unpack_kwargs":false,"variables":[]}}},"current_thread":{".class":"SymbolTableNode","cross_ref":"threading.current_thread","kind":"Gdef"},"datetime":{".class":"SymbolTableNode","cross_ref":"datetime.datetime","kind":"Gdef"},"generate_fingerprint_from_browser_json":{".class":"SymbolTableNode","kind":"Gdef","node":{".class":"FuncDef","abstract_status":0,"arg_kinds":[0],"arg_names":["filename"],"dataclass_transform_spec":null,"flags":[],"fullname":"pyadtpulse.util.generate_fingerprint_from_browser_json","name":"generate_fingerprint_from_browser_json","type":{".class":"CallableType","arg_kinds":[0],"arg_names":["filename"],"arg_types":["builtins.str"],"bound_args":[],"def_extras":{"first_arg":null},"fallback":"builtins.function","from_concatenate":false,"implicit":false,"is_ellipsis_args":false,"name":"generate_fingerprint_from_browser_json","ret_type":"builtins.str","type_guard":null,"unpack_kwargs":false,"variables":[]}}},"generate_random_fingerprint":{".class":"SymbolTableNode","kind":"Gdef","node":{".class":"FuncDef","abstract_status":0,"arg_kinds":[],"arg_names":[],"dataclass_transform_spec":null,"flags":[],"fullname":"pyadtpulse.util.generate_random_fingerprint","name":"generate_random_fingerprint","type":{".class":"CallableType","arg_kinds":[],"arg_names":[],"arg_types":[],"bound_args":[],"def_extras":{"first_arg":null},"fallback":"builtins.function","from_concatenate":false,"implicit":false,"is_ellipsis_args":false,"name":"generate_random_fingerprint","ret_type":"builtins.str","type_guard":null,"unpack_kwargs":false,"variables":[]}}},"handle_response":{".class":"SymbolTableNode","kind":"Gdef","node":{".class":"FuncDef","abstract_status":0,"arg_kinds":[0,0,0],"arg_names":["response","level","error_message"],"dataclass_transform_spec":null,"flags":[],"fullname":"pyadtpulse.util.handle_response","name":"handle_response","type":{".class":"CallableType","arg_kinds":[0,0,0],"arg_names":["response","level","error_message"],"arg_types":[{".class":"UnionType","items":["aiohttp.client_reqrep.ClientResponse",{".class":"NoneType"}]},"builtins.int","builtins.str"],"bound_args":[],"def_extras":{"first_arg":null},"fallback":"builtins.function","from_concatenate":false,"implicit":false,"is_ellipsis_args":false,"name":"handle_response","ret_type":"builtins.bool","type_guard":null,"unpack_kwargs":false,"variables":[]}}},"logging":{".class":"SymbolTableNode","cross_ref":"logging","kind":"Gdef"},"make_soup":{".class":"SymbolTableNode","kind":"Gdef","node":{".class":"FuncDef","abstract_status":0,"arg_kinds":[0,0,0],"arg_names":["response","level","error_message"],"dataclass_transform_spec":null,"flags":["is_coroutine"],"fullname":"pyadtpulse.util.make_soup","name":"make_soup","type":{".class":"CallableType","arg_kinds":[0,0,0],"arg_names":["response","level","error_message"],"arg_types":[{".class":"UnionType","items":["aiohttp.client_reqrep.ClientResponse",{".class":"NoneType"}]},"builtins.int","builtins.str"],"bound_args":[],"def_extras":{"first_arg":null},"fallback":"builtins.function","from_concatenate":false,"implicit":false,"is_ellipsis_args":false,"name":"make_soup","ret_type":{".class":"Instance","args":[{".class":"AnyType","missing_import_name":null,"source_any":null,"type_of_any":6},{".class":"AnyType","missing_import_name":null,"source_any":null,"type_of_any":6},{".class":"UnionType","items":[{".class":"AnyType","missing_import_name":"pyadtpulse.util.BeautifulSoup","source_any":null,"type_of_any":3},{".class":"NoneType"}]}],"type_ref":"typing.Coroutine"},"type_guard":null,"unpack_kwargs":false,"variables":[]}}},"parse_pulse_datetime":{".class":"SymbolTableNode","kind":"Gdef","node":{".class":"FuncDef","abstract_status":0,"arg_kinds":[0],"arg_names":["datestring"],"dataclass_transform_spec":null,"flags":[],"fullname":"pyadtpulse.util.parse_pulse_datetime","name":"parse_pulse_datetime","type":{".class":"CallableType","arg_kinds":[0],"arg_names":["datestring"],"arg_types":["builtins.str"],"bound_args":[],"def_extras":{"first_arg":null},"fallback":"builtins.function","from_concatenate":false,"implicit":false,"is_ellipsis_args":false,"name":"parse_pulse_datetime","ret_type":"datetime.datetime","type_guard":null,"unpack_kwargs":false,"variables":[]}}},"randint":{".class":"SymbolTableNode","cross_ref":"random.randint","kind":"Gdef"},"relativedelta":{".class":"SymbolTableNode","cross_ref":"dateutil.relativedelta","kind":"Gdef"},"remove_prefix":{".class":"SymbolTableNode","kind":"Gdef","node":{".class":"FuncDef","abstract_status":0,"arg_kinds":[0,0],"arg_names":["text","prefix"],"dataclass_transform_spec":null,"flags":[],"fullname":"pyadtpulse.util.remove_prefix","name":"remove_prefix","type":{".class":"CallableType","arg_kinds":[0,0],"arg_names":["text","prefix"],"arg_types":["builtins.str","builtins.str"],"bound_args":[],"def_extras":{"first_arg":null},"fallback":"builtins.function","from_concatenate":false,"implicit":false,"is_ellipsis_args":false,"name":"remove_prefix","ret_type":"builtins.str","type_guard":null,"unpack_kwargs":false,"variables":[]}}},"string":{".class":"SymbolTableNode","cross_ref":"string","kind":"Gdef"},"sys":{".class":"SymbolTableNode","cross_ref":"sys","kind":"Gdef"},"timedelta":{".class":"SymbolTableNode","cross_ref":"datetime.timedelta","kind":"Gdef"},"urlsafe_b64encode":{".class":"SymbolTableNode","cross_ref":"base64.urlsafe_b64encode","kind":"Gdef"}},"path":"/home/rlippmann/git/pyadtpulse/pyadtpulse/util.py"}