[
    {
        "name": "iTerm",
        "cmd": "open '/Applications/iTerm.app'",
        "key": "<cmd>+1",
        "type": "launch"
    },
    {
        "name": "VSCode",
        "cmd": "open '/Applications/Visual Studio Code.app'",
        "key": "<cmd>+2",
        "type": "launch"

    },
    {
        "name": "Chrome",
        "cmd": "open '/Applications/Google Chrome.app'",
        "key": "<cmd>+3",
        "type": "launch"
    },
    {
        "name": "Finder",
        "cmd": "open /Users/david",
        "key": "<cmd>+e",
        "type": "launch"

    },
    {
        "name": "FireFox",
        "cmd": "open '/Applications/Firefox.app'",
        "key": "<cmd>+4",
        "type": "launch"
    }    
]